[
    {
        "id": "suburb",
        "name": "locations.suburb.name",
        "description": "locations.suburb.description",
        "required_level": 0,
        "event_files": [
            "shared/config/events/suburb_events.json",
            "shared/config/events/common_events.json"
        ]
    },
    {
        "id": "forest",
        "name": "locations.forest.name",
        "description": "locations.forest.description",
        "required_level": 2,
        "event_files": [
            "shared/config/events/forest_events.json",
            "shared/config/events/common_events.json"
        ]
    },
    {
        "id": "lake",
        "name": "locations.lake.name",
        "description": "locations.lake.description",
        "required_level": 3,
        "event_files": [
            "shared/config/events/lake_events.json",
            "shared/config/events/common_events.json"
        ]
    },
    {
        "id": "cave",
        "name": "locations.cave.name",
        "description": "locations.cave.description",
        "required_level": 4,
        "event_files": [
            "shared/config/events/cave_events.json",
            "shared/config/events/common_events.json"
        ]
    },
    {
        "id": "abandoned_mine",
        "name": "locations.abandoned_mine.name",
        "description": "locations.abandoned_mine.description",
        "required_level": 5,
        "event_files": [
            "shared/config/events/abandoned_mine_events.json",
            "shared/config/events/common_events.json"
        ]
    },
    {
        "id": "volcano",
        "name": "locations.volcano.name",
        "description": "locations.volcano.description",
        "required_level": 6,
        "event_files": [
            "shared/config/events/volcano_events.json",
            "shared/config/events/common_events.json"
        ]
    },
    {
        "id": "ancient_altar",
        "name": "locations.ancient_altar.name",
        "description": "locations.ancient_altar.description",
        "required_level": 10,
        "event_files": [
            "shared/config/events/ancient_altar_events.json",
            "shared/config/events/common_events.json"
        ]
    },
    {
        "id": "abandoned_village",
        "name": "locations.abandoned_village.name",
        "description": "locations.abandoned_village.description",
        "required_level": 15,
        "event_files": [
            "shared/config/events/abandoned_village_events.json",
            "shared/config/events/common_events.json"
        ]
    }
]
